logdetective/__init__.py
logdetective/constants.py
logdetective/drain3.ini
logdetective/extractors.py
logdetective/logdetective.py
logdetective/models.py
logdetective/prompts/message_template.j2
logdetective/prompts/snippet_message_template.j2
logdetective/prompts/snippet_system_prompt.j2
logdetective/prompts/staged_message_template.j2
logdetective/prompts/staged_system_prompt.j2
logdetective/prompts/system_prompt.j2
logdetective/prompts-summary-first.yml
logdetective/prompts-summary-only.yml
logdetective/prompts.py
logdetective/prompts.yml
logdetective/remote_log.py
logdetective/server/__init__.py
logdetective/server/compressors.py
logdetective/server/config.py
logdetective/server/database/__init__.py
logdetective/server/database/base.py
logdetective/server/database/models/__init__.py
logdetective/server/database/models/exceptions.py
logdetective/server/database/models/koji.py
logdetective/server/database/models/merge_request_jobs.py
logdetective/server/database/models/metrics.py
logdetective/server/emoji.py
logdetective/server/exceptions.py
logdetective/server/gitlab.py
logdetective/server/koji.py
logdetective/server/llm.py
logdetective/server/metric.py
logdetective/server/models.py
logdetective/server/server.py
logdetective/server/templates/base_response.html.j2
logdetective/server/templates/gitlab_full_comment.md.j2
logdetective/server/templates/gitlab_short_comment.md.j2
logdetective/server/utils.py
logdetective/skip_snippets.yml
logdetective/utils.py
logdetective-3.1.0.dist-info/METADATA
logdetective-3.1.0.dist-info/WHEEL
logdetective-3.1.0.dist-info/entry_points.txt
logdetective-3.1.0.dist-info/licenses/LICENSE
logdetective-3.1.0.dist-info/RECORD
