Metadata-Version: 2.4
Name: logdetective
Version: 3.1.0
Summary: Analyze logs with a template miner and an LLM to discover errors and suggest solutions.
License: Apache-2.0
License-File: LICENSE
Author: Jiri Podivin
Author-email: jpodivin@gmail.com
Requires-Python: >=3.11,<4.0
Classifier: Development Status :: 5 - Production/Stable
Classifier: Environment :: Console
Classifier: Intended Audience :: Developers
Classifier: License :: OSI Approved :: Apache Software License
Classifier: Natural Language :: English
Classifier: Programming Language :: Python :: 3
Classifier: Programming Language :: Python :: 3.11
Classifier: Programming Language :: Python :: 3.12
Classifier: Programming Language :: Python :: 3.13
Classifier: Programming Language :: Python :: 3.14
Classifier: Topic :: Internet :: Log Analysis
Classifier: Topic :: Scientific/Engineering :: Artificial Intelligence
Classifier: Topic :: Software Development :: Debuggers
Provides-Extra: server
Provides-Extra: server-testing
Provides-Extra: testing
Requires-Dist: aiohttp (>=3.7.4,<4.0.0)
Requires-Dist: aiolimiter (>=1.0.0,<2.0.0) ; extra == "server" or extra == "server-testing"
Requires-Dist: aioresponses (>=0.7.8,<0.8.0) ; extra == "testing"
Requires-Dist: alembic (>=1.13.3,<2.0.0) ; extra == "server" or extra == "server-testing"
Requires-Dist: asciidoc[testing] (>=10.2.1,<11.0.0) ; extra == "testing"
Requires-Dist: asyncpg (>=0.30.0,<1.0.0) ; extra == "server" or extra == "server-testing"
Requires-Dist: backoff (==2.2.1) ; extra == "server" or extra == "server-testing"
Requires-Dist: drain3 (>=0.9.11,<0.10.0)
Requires-Dist: fastapi (>=0.111.1,<1.0.0) ; extra == "server" or extra == "server-testing"
Requires-Dist: flexmock (>=0.12.2,<0.13.0) ; extra == "testing"
Requires-Dist: huggingface-hub (>=0.23.0,<1.4.0)
Requires-Dist: koji (>=1.35.0,<2.0.0) ; extra == "server" or extra == "server-testing"
Requires-Dist: llama-cpp-python (>0.2.56,!=0.2.86,<1.0.0)
Requires-Dist: numpy (>=1.26.0)
Requires-Dist: openai (>=1.82.1,<2.0.0) ; extra == "server" or extra == "server-testing"
Requires-Dist: pydantic (>=2.8.2,<3.0.0)
Requires-Dist: pytest (>=8.4.1,<9.0.0) ; extra == "testing"
Requires-Dist: pytest-asyncio (>=1.1.0,<2.0.0) ; extra == "testing"
Requires-Dist: pytest-cov[testing] (>=7.0.0,<8.0.0) ; extra == "testing"
Requires-Dist: pytest-mock (>=3.14.1,<4.0.0) ; extra == "server-testing"
Requires-Dist: python-gitlab (>=4.4.0)
Requires-Dist: pyyaml (>=6.0.1,<7.0.0)
Requires-Dist: responses (>=0.25.7,<0.26.0) ; extra == "server-testing"
Requires-Dist: sentry-sdk[fastapi] (>=2.17.0,<3.0.0) ; extra == "server" or extra == "server-testing"
Requires-Dist: sqlalchemy (>=2.0.36,<3.0.0) ; extra == "server" or extra == "server-testing"
Project-URL: homepage, https://github.com/fedora-copr/logdetective
Project-URL: issues, https://github.com/fedora-copr/logdetective/issues
